weather_tty/__init__.py
weather_tty/api.py
weather_tty/cli.py
weather_tty/formatting.py
weather_tty-0.1.0.dist-info/METADATA
weather_tty-0.1.0.dist-info/WHEEL
weather_tty-0.1.0.dist-info/entry_points.txt
weather_tty-0.1.0.dist-info/licenses/LICENSE
weather_tty-0.1.0.dist-info/RECORD
