Metadata-Version: 2.4
Name: weather-tty
Version: 0.1.0
Summary: Tiny CLI to print today's weather for your terminal (Open-Meteo, zero API key).
Author: Crack del universo
License: MIT
License-File: LICENSE
Requires-Python: >=3.10
Requires-Dist: httpx>=0.27
Requires-Dist: rich>=13.7
Requires-Dist: typer>=0.12
